odoo9_addon_stock_split_picking-9.0.1.0.0.99.dev2-py3.8-nspkg.pth
odoo_addons/stock_split_picking/README.rst
odoo_addons/stock_split_picking/__init__.py
odoo_addons/stock_split_picking/__openerp__.py
odoo_addons/stock_split_picking/i18n/ca.po
odoo_addons/stock_split_picking/i18n/de.po
odoo_addons/stock_split_picking/i18n/es.po
odoo_addons/stock_split_picking/i18n/es_MX.po
odoo_addons/stock_split_picking/i18n/fi.po
odoo_addons/stock_split_picking/i18n/fr.po
odoo_addons/stock_split_picking/i18n/hr.po
odoo_addons/stock_split_picking/i18n/it.po
odoo_addons/stock_split_picking/i18n/nl_NL.po
odoo_addons/stock_split_picking/i18n/pt.po
odoo_addons/stock_split_picking/i18n/pt_BR.po
odoo_addons/stock_split_picking/i18n/sl.po
odoo_addons/stock_split_picking/i18n/stock_split_picking.pot
odoo_addons/stock_split_picking/i18n/tr.po
odoo_addons/stock_split_picking/i18n/tr_TR.po
odoo_addons/stock_split_picking/models/__init__.py
odoo_addons/stock_split_picking/models/stock_picking.py
odoo_addons/stock_split_picking/static/description/icon.png
odoo_addons/stock_split_picking/tests/__init__.py
odoo_addons/stock_split_picking/tests/test_stock_split_picking.py
odoo_addons/stock_split_picking/views/stock_partial_picking.xml
odoo9_addon_stock_split_picking-9.0.1.0.0.99.dev2.dist-info/METADATA
odoo9_addon_stock_split_picking-9.0.1.0.0.99.dev2.dist-info/WHEEL
odoo9_addon_stock_split_picking-9.0.1.0.0.99.dev2.dist-info/namespace_packages.txt
odoo9_addon_stock_split_picking-9.0.1.0.0.99.dev2.dist-info/top_level.txt
odoo9_addon_stock_split_picking-9.0.1.0.0.99.dev2.dist-info/RECORD
