Metadata-Version: 2.1
Name: odoo9-addon-stock-split-picking
Version: 9.0.1.0.0.99.dev2
Summary: Split a picking in two not transferred pickings
Home-page: http://www.camptocamp.com
Author: Camptocamp, Tecnativa, Odoo Community Association (OCA)
Author-email: support@odoo-community.org
License: AGPL-3
Platform: UNKNOWN
Classifier: Programming Language :: Python
Classifier: Framework :: Odoo
Classifier: Framework :: Odoo :: 9.0
Classifier: License :: OSI Approved :: GNU Affero General Public License v3
Requires-Python: ~=2.7
Requires-Dist: odoo (<9.1a,>=9.0a)
